.DS_Store
st_schedule_component/__init__.py
st_schedule_component/example.py
st_schedule_component/frontend/build/asset-manifest.json
st_schedule_component/frontend/build/bootstrap.min.css
st_schedule_component/frontend/build/index.html
st_schedule_component/frontend/build/static/css/main.c26e95d3.css
st_schedule_component/frontend/build/static/css/main.c26e95d3.css.map
st_schedule_component/frontend/build/static/js/main.7efbd2d5.js
st_schedule_component/frontend/build/static/js/main.7efbd2d5.js.LICENSE.txt
st_schedule_component/frontend/build/static/js/main.7efbd2d5.js.map
streamlit_schedule_selector/__init__.py
streamlit_schedule_selector/example.py
streamlit_week_calendar/__init__.py
streamlit_week_calendar/example.py
streamlit_week_calendar/frontend/build/asset-manifest.json
streamlit_week_calendar/frontend/build/bootstrap.min.css
streamlit_week_calendar/frontend/build/index.html
streamlit_week_calendar/frontend/build/static/css/main.c26e95d3.css
streamlit_week_calendar/frontend/build/static/css/main.c26e95d3.css.map
streamlit_week_calendar/frontend/build/static/js/main.41f791eb.js
streamlit_week_calendar/frontend/build/static/js/main.41f791eb.js.LICENSE.txt
streamlit_week_calendar/frontend/build/static/js/main.41f791eb.js.map
streamlit_week_calendar/frontend/build/static/js/main.4f8d315e.js
streamlit_week_calendar/frontend/build/static/js/main.4f8d315e.js.LICENSE.txt
streamlit_week_calendar/frontend/build/static/js/main.4f8d315e.js.map
streamlit_week_calendar/frontend/build/static/js/main.7efbd2d5.js
streamlit_week_calendar/frontend/build/static/js/main.7efbd2d5.js.LICENSE.txt
streamlit_week_calendar/frontend/build/static/js/main.7efbd2d5.js.map
streamlit_week_calendar/frontend/build/static/js/main.86955032.js
streamlit_week_calendar/frontend/build/static/js/main.86955032.js.LICENSE.txt
streamlit_week_calendar/frontend/build/static/js/main.86955032.js.map
streamlit_week_calendar-0.0.5.post2.dist-info/LICENSE
streamlit_week_calendar-0.0.5.post2.dist-info/METADATA
streamlit_week_calendar-0.0.5.post2.dist-info/WHEEL
streamlit_week_calendar-0.0.5.post2.dist-info/top_level.txt
streamlit_week_calendar-0.0.5.post2.dist-info/RECORD
