Metadata-Version: 2.1
Name: streamlit-week-calendar
Version: 0.0.5.post2
Summary: Streamlit component that allows you to use react-schedule-selector
Home-page: 
Author: Zolyer
Author-email: tannaim@kyonggi.ac.kr
Requires-Python: >=3.7
License-File: LICENSE
Requires-Dist: streamlit >=0.63
Provides-Extra: devel
Requires-Dist: wheel ; extra == 'devel'
Requires-Dist: pytest ==7.4.0 ; extra == 'devel'
Requires-Dist: playwright ==1.39.0 ; extra == 'devel'
Requires-Dist: requests ==2.31.0 ; extra == 'devel'
Requires-Dist: pytest-playwright-snapshot ==1.0 ; extra == 'devel'
Requires-Dist: pytest-rerunfailures ==12.0 ; extra == 'devel'
